google_ads_server.py
google_ads_mcp_bratrax-1.0.7.dist-info/licenses/LICENSE
google_ads_mcp_bratrax-1.0.7.dist-info/METADATA
google_ads_mcp_bratrax-1.0.7.dist-info/WHEEL
google_ads_mcp_bratrax-1.0.7.dist-info/entry_points.txt
google_ads_mcp_bratrax-1.0.7.dist-info/top_level.txt
google_ads_mcp_bratrax-1.0.7.dist-info/RECORD
