Metadata-Version: 2.4
Name: google-ads-mcp-bratrax
Version: 1.0.7
Summary: Google Ads API integration for Model Context Protocol (MCP) with refresh token authentication
Author-email: Bratrax <bratrax@example.com>
Maintainer-email: Bratrax <bratrax@example.com>
License: MIT
Project-URL: Homepage, https://github.com/bratrax/google-ads-mcp-bratrax
Project-URL: Documentation, https://github.com/bratrax/google-ads-mcp-bratrax#readme
Project-URL: Repository, https://github.com/bratrax/google-ads-mcp-bratrax
Project-URL: Bug Tracker, https://github.com/bratrax/google-ads-mcp-bratrax/issues
Project-URL: Changelog, https://github.com/bratrax/google-ads-mcp-bratrax/blob/main/CHANGELOG.md
Keywords: mcp,google-ads,google-ads-api,claude,refresh-token,oauth
Classifier: Development Status :: 5 - Production/Stable
Classifier: Intended Audience :: Developers
Classifier: Intended Audience :: System Administrators
Classifier: License :: OSI Approved :: MIT License
Classifier: Operating System :: OS Independent
Classifier: Programming Language :: Python :: 3
Classifier: Programming Language :: Python :: 3.11
Classifier: Programming Language :: Python :: 3.12
Classifier: Topic :: Internet :: WWW/HTTP :: Indexing/Search
Classifier: Topic :: Software Development :: Libraries :: Python Modules
Classifier: Topic :: Office/Business :: Financial :: Spreadsheet
Requires-Python: >=3.11
License-File: LICENSE
Requires-Dist: google-auth>=2.25.2
Requires-Dist: google-auth-oauthlib>=1.1.0
Requires-Dist: requests>=2.31.0
Requires-Dist: python-dotenv>=1.0.0
Requires-Dist: mcp>=1.0.0
Requires-Dist: pydantic>=2.0.0
Provides-Extra: dev
Requires-Dist: pytest>=7.0.0; extra == "dev"
Requires-Dist: pytest-asyncio>=0.21.0; extra == "dev"
Requires-Dist: black>=23.0.0; extra == "dev"
Requires-Dist: flake8>=6.0.0; extra == "dev"
Requires-Dist: mypy>=1.0.0; extra == "dev"
Dynamic: license-file
